embedl_hub/__init__.py
embedl_hub/cli/app.py
embedl_hub/cli/benchmark.py
embedl_hub/cli/compile.py
embedl_hub/cli/export.py
embedl_hub/cli/init.py
embedl_hub/cli/list_devices.py
embedl_hub/cli/quantize.py
embedl_hub/cli/tune.py
embedl_hub/cli/utils.py
embedl_hub/core/__init__.py
embedl_hub/core/benchmark.py
embedl_hub/core/compile.py
embedl_hub/core/config.py
embedl_hub/core/context.py
embedl_hub/core/hub_logging.py
embedl_hub/core/default_configs/__init__.py
embedl_hub/core/default_configs/quantization_config.yaml.j2
embedl_hub/core/default_configs/tuning_config.yaml.j2
embedl_hub/core/hardware/__init__.py
embedl_hub/core/hardware/qualcomm_ai_hub.py
embedl_hub/core/quantization/quantization_config.py
embedl_hub/core/quantization/quantize.py
embedl_hub/core/tuning/__init__.py
embedl_hub/core/tuning/load_model.py
embedl_hub/core/tuning/save_model.py
embedl_hub/core/tuning/tuner.py
embedl_hub/core/tuning/tuning_config.py
embedl_hub/core/tuning/hyperparameters/__init__.py
embedl_hub/core/tuning/hyperparameters/batch_size.py
embedl_hub/core/tuning/hyperparameters/learning_rate.py
embedl_hub/tracking/__init__.py
embedl_hub/tracking/client.py
embedl_hub/tracking/rest_api.py
embedl_hub/tracking/utils.py
embedl_hub_cli-2025.6.0.dev1.dist-info/licenses/LICENSE
embedl_hub_cli-2025.6.0.dev1.dist-info/licenses/NOTICE
embedl_hub_cli-2025.6.0.dev1.dist-info/METADATA
embedl_hub_cli-2025.6.0.dev1.dist-info/WHEEL
embedl_hub_cli-2025.6.0.dev1.dist-info/entry_points.txt
embedl_hub_cli-2025.6.0.dev1.dist-info/top_level.txt
embedl_hub_cli-2025.6.0.dev1.dist-info/RECORD
