Metadata-Version: 2.4
Name: embedl-hub-cli
Version: 2025.6.0.dev1
Summary: The official Embedl Hub Python client library.
Author-email: Embedl AB <support@embedl.com>
Project-URL: Homepage, https://hub.embedl.com
Project-URL: Documentation, https://hub.embedl.com/docs
Classifier: Development Status :: 1 - Planning
Classifier: Intended Audience :: Developers
Classifier: License :: Other/Proprietary License
Classifier: Programming Language :: Python :: 3
Classifier: Programming Language :: Python :: 3 :: Only
Classifier: Programming Language :: Python :: 3.11
Classifier: Programming Language :: Python :: 3.12
Classifier: Topic :: Scientific/Engineering :: Artificial Intelligence
Classifier: Topic :: Software Development :: Embedded Systems
Classifier: Topic :: Software Development :: Libraries
Requires-Python: >=3.11
License-File: LICENSE
License-File: NOTICE
Requires-Dist: Jinja2>=3.1.5
Requires-Dist: lightning>=2.5.0
Requires-Dist: mergedeep>=1.3.4
Requires-Dist: onnx>=1.17
Requires-Dist: onnxruntime>=1.18
Requires-Dist: pydantic>=2.8.2
Requires-Dist: PyYAML~=6.0.2
Requires-Dist: qai-hub>=0.28.0
Requires-Dist: requests>=2.32.3
Requires-Dist: rich>=13.7
Requires-Dist: timm>=1.0.15
Requires-Dist: torch>=2.6.0
Requires-Dist: torchvision>=0.21.0
Requires-Dist: typer[all]>=0.12.0
Provides-Extra: dev
Requires-Dist: mkdocs; extra == "dev"
Requires-Dist: mkdocs-material; extra == "dev"
Requires-Dist: mkdocstrings[python]; extra == "dev"
Requires-Dist: pytest; extra == "dev"
Requires-Dist: ruff; extra == "dev"
Dynamic: license-file
